watchbot_progress/__init__.py
watchbot_progress/cli.py
watchbot_progress/errors.py
watchbot_progress/main.py
watchbot_progress/utils.py
watchbot_progress/backends/__init__.py
watchbot_progress/backends/base.py
watchbot_progress/backends/dynamodb.py
watchbot_progress/backends/redis.py
watchbot_progress-0.9.1.dist-info/LICENSE
watchbot_progress-0.9.1.dist-info/METADATA
watchbot_progress-0.9.1.dist-info/WHEEL
watchbot_progress-0.9.1.dist-info/entry_points.txt
watchbot_progress-0.9.1.dist-info/top_level.txt
watchbot_progress-0.9.1.dist-info/RECORD
