Metadata-Version: 2.1
Name: watchbot-progress
Version: 0.9.1
Summary: Watchbot reduce-mode helpers for python
Home-page: https://github.com/mapbox/watchbot-progress-py
Author: Matthew Perry
Author-email: perry@mapbox.com
License: MIT
Platform: UNKNOWN
Requires-Dist: boto3
Requires-Dist: redis (~=2.0)
Provides-Extra: test
Requires-Dist: pytest ; extra == 'test'
Requires-Dist: pytest-cov ; extra == 'test'
Requires-Dist: mock ; extra == 'test'
Requires-Dist: click ; extra == 'test'
Requires-Dist: mockredispy ; extra == 'test'
